pycomplete-0.4.0.dist-info/METADATA
pycomplete-0.4.0.dist-info/WHEEL
pycomplete-0.4.0.dist-info/entry_points.txt
pycomplete-0.4.0.dist-info/licenses/LICENSE
pycomplete/__init__.py
pycomplete/__main__.py
pycomplete/getters.py
pycomplete/templates/__init__.py
pycomplete/templates/bash.tpl
pycomplete/templates/fish.tpl
pycomplete/templates/powershell.tpl
pycomplete/templates/zsh.tpl
pycomplete-0.4.0.dist-info/RECORD
