Metadata-Version: 2.1
Name: pycomplete
Version: 0.4.0
Summary: A Python library to generate static completion scripts for your CLI app
Keywords: cli shell
Author-Email: Frost Ming <mianghong@gmail.com>
License: BSD-3-Clause
Classifier: Development Status :: 3 - Alpha
Classifier: Programming Language :: Python :: 3
Project-URL: Homepage, https://github.com/frostming/pycomplete
Requires-Python: >=3.7
